hoisaai/layer_0/tensor.py
hoisaai/layer_1/model.py
hoisaai/layer_1/sample.py
hoisaai/layer_1/dataframe/data_preprocessing.py
hoisaai/layer_1/dataframe/data_source.py
hoisaai/layer_1/learning_model/supervised/error.py
hoisaai/layer_1/learning_model/supervised/linear.py
hoisaai/layer_1/learning_model/supervised/supervised.py
HoiSaAI-0.0.2.dist-info/LICENSE
HoiSaAI-0.0.2.dist-info/METADATA
HoiSaAI-0.0.2.dist-info/WHEEL
HoiSaAI-0.0.2.dist-info/top_level.txt
HoiSaAI-0.0.2.dist-info/RECORD
