Metadata-Version: 2.1
Name: HoiSaAI
Version: 0.0.2
Summary: HoiSaAI is an open-source artificial intelligence (AI) project designed to harness the power of distributed computing for solving complex problems efficiently
Author-email: Mike Mo Shun Cheng <u3568882@connect.hku.hk>
Project-URL: Homepage, https://github.com/mikecheng18/hoisaai
Project-URL: Issues, https://github.com/mikecheng18/hoisaai/issues
Classifier: Programming Language :: Python :: 3
Classifier: Operating System :: OS Independent
Requires-Python: >=3.11
License-File: LICENSE
